run80by24/common/__init__.py
run80by24/common/messages.py
run80by24/common/id_generator/__init__.py
run80by24/common/id_generator/words.txt
run80by24_common-0.2.0.dist-info/DESCRIPTION.rst
run80by24_common-0.2.0.dist-info/METADATA
run80by24_common-0.2.0.dist-info/RECORD
run80by24_common-0.2.0.dist-info/WHEEL
run80by24_common-0.2.0.dist-info/metadata.json
run80by24_common-0.2.0.dist-info/top_level.txt
