Metadata-Version: 2.0
Name: run80by24-common
Version: 0.2.0
Summary: Protocol and other common functions for run28by24-client and run80by24-server.
Home-page: https://80by24.net
Author: Sander Evers
Author-email: UNKNOWN
License: UNKNOWN
Keywords: terminal console
Platform: UNKNOWN
Classifier: Development Status :: 3 - Alpha
Classifier: Intended Audience :: Developers
Classifier: Topic :: Software Development :: Build Tools
Classifier: License :: OSI Approved :: GNU Affero General Public License v3 or later (AGPLv3+)
Classifier: Programming Language :: Python :: 3.4
